LICENSE
MANIFEST.in
README
setup.py
src/sleipnir/__init__.py
src/sleipnir.core.egg-info/PKG-INFO
src/sleipnir.core.egg-info/SOURCES.txt
src/sleipnir.core.egg-info/dependency_links.txt
src/sleipnir.core.egg-info/namespace_packages.txt
src/sleipnir.core.egg-info/not-zip-safe
src/sleipnir.core.egg-info/requires.txt
src/sleipnir.core.egg-info/top_level.txt
src/sleipnir/core/__init__.py
src/sleipnir/core/_enum.py
src/sleipnir/core/async.py
src/sleipnir/core/callback.py
src/sleipnir/core/constants.py
src/sleipnir/core/decorators.py
src/sleipnir/core/evaluators.py
src/sleipnir/core/event.py
src/sleipnir/core/factory.py
src/sleipnir/core/imports.py
src/sleipnir/core/log.py
src/sleipnir/core/memoizer.py
src/sleipnir/core/operators.py
src/sleipnir/core/parser.py
src/sleipnir/core/singleton.py
src/sleipnir/core/thread.py
src/sleipnir/core/utils.py
src/sleipnir/core/visitor.py